pygreynoisev1/__init__.py
pygreynoisev1/api.py
pygreynoisev1/cli.py
pygreynoisev1-0.1.dist-info/LICENSE
pygreynoisev1-0.1.dist-info/METADATA
pygreynoisev1-0.1.dist-info/WHEEL
pygreynoisev1-0.1.dist-info/entry_points.txt
pygreynoisev1-0.1.dist-info/top_level.txt
pygreynoisev1-0.1.dist-info/RECORD
