Metadata-Version: 2.1
Name: pygreynoisev1
Version: 0.1
Summary: Python wrapper around the GreyNoise APO
Home-page: https://github.com/Te-k/pygreynoisev1
Author: Tek
Author-email: tek@randhome.io
License: MIT
Keywords: security
Platform: UNKNOWN
Classifier: Programming Language :: Python :: 3
Classifier: License :: OSI Approved :: MIT License
Classifier: Operating System :: OS Independent
Requires-Dist: requests
